commission_setting_mcp/__init__.py
commission_setting_mcp/feishu_util.py
commission_setting_mcp/mcp_server.py
commission_setting_mcp/playwright_commission.py
shared/__init__.py
shared/browser_manager.py
shared/coze_api.py
shared/error_handler.py
shared/log_util.py
commission_setting_mcp-0.0.20.dist-info/METADATA
commission_setting_mcp-0.0.20.dist-info/WHEEL
commission_setting_mcp-0.0.20.dist-info/entry_points.txt
commission_setting_mcp-0.0.20.dist-info/top_level.txt
commission_setting_mcp-0.0.20.dist-info/RECORD
