Metadata-Version: 2.4
Name: commission-setting-mcp
Version: 0.0.20
Summary: 佣金设置MCP工具
Requires-Python: >=3.10
Requires-Dist: httpx==0.28.1
Requires-Dist: loguru==0.5.3
Requires-Dist: mcp[cli]==1.6.0
Requires-Dist: playwright==1.51.0
Requires-Dist: python-dotenv==1.0.0
Requires-Dist: twine>=6.1.0
